mb_rag/__init__.py
mb_rag/basic.py
mb_rag/prompts_bank.py
mb_rag/version.py
mb_rag/agents/__init__.py
mb_rag/agents/bb_autolabel.py
mb_rag/agents/deep_agents.py
mb_rag/agents/get_langsmith.py
mb_rag/agents/middleware.py
mb_rag/agents/run_agent.py
mb_rag/agents/seg_autolabel.py
mb_rag/agents/sql_agents.py
mb_rag/agents/tools.py
mb_rag/agents/web_browser_agent.py
mb_rag/chatbot/__init__.py
mb_rag/chatbot/chains.py
mb_rag/chatbot/conversation.py
mb_rag/rag/__init__.py
mb_rag/rag/embeddings.py
mb_rag/utils/__init__.py
mb_rag/utils/all_data_extract.py
mb_rag/utils/bounding_box.py
mb_rag/utils/document_extract.py
mb_rag/utils/extra.py
mb_rag/utils/llm_wrapper.py
mb_rag/utils/pdf_extract.py
mb_rag/utils/viewer.py
mb_rag-1.1.99.dist-info/METADATA
mb_rag-1.1.99.dist-info/WHEEL
mb_rag-1.1.99.dist-info/top_level.txt
mb_rag-1.1.99.dist-info/RECORD
