Metadata-Version: 2.4
Name: mb_rag
Version: 1.1.99
Summary: RAG function file
Author: ['Malav Bateriwala']
Requires-Python: >=3.8
Requires-Dist: mb_base
Dynamic: author
Dynamic: requires-dist
Dynamic: requires-python
Dynamic: summary
